python_sdk_remote/__init__.py
python_sdk_remote/constants.py
python_sdk_remote/constants_src_mini_logger_and_logger.py
python_sdk_remote/http_response.py
python_sdk_remote/is_test_data.py
python_sdk_remote/item.py
python_sdk_remote/mini_logger.py
python_sdk_remote/our_object.py
python_sdk_remote/unified_json.py
python_sdk_remote/utilities.py
python_sdk_remote/valid_json_versions.py
python_sdk_remote/validate_environment.py
python_sdk_remote-0.0.155.dist-info/METADATA
python_sdk_remote-0.0.155.dist-info/WHEEL
python_sdk_remote-0.0.155.dist-info/top_level.txt
python_sdk_remote-0.0.155.dist-info/RECORD
