Metadata-Version: 2.4
Name: python-sdk-remote
Version: 0.0.155
Summary: PyPI Package for Circles Python SDK Local Python
Home-page: https://github.com/circles-zone/python-sdk-remote-python-package
Author: Circles
Author-email: info@circlez.ai
Classifier: Programming Language :: Python :: 3
Classifier: Operating System :: OS Independent
Requires-Dist: requests
Requires-Dist: python-dotenv
Requires-Dist: url-remote
Requires-Dist: pyjwt
Dynamic: author
Dynamic: author-email
Dynamic: classifier
Dynamic: description
Dynamic: description-content-type
Dynamic: home-page
Dynamic: requires-dist
Dynamic: summary
